cagrex/__init__.py
cagrex/cagr.py
cagrex-0.1.4.dist-info/DESCRIPTION.rst
cagrex-0.1.4.dist-info/METADATA
cagrex-0.1.4.dist-info/RECORD
cagrex-0.1.4.dist-info/WHEEL
cagrex-0.1.4.dist-info/metadata.json
cagrex-0.1.4.dist-info/top_level.txt
