Metadata-Version: 2.0
Name: cagrex
Version: 0.1.4
Summary: UNKNOWN
Home-page: UNKNOWN
Author: UNKNOWN
Author-email: UNKNOWN
License: UNKNOWN
Platform: UNKNOWN
Requires-Dist: requests
Requires-Dist: bs4
Requires-Dist: mechanicalsoup
